MANIFEST.in
README.rst
setup.cfg
setup.py
tayrakit/__init__.py
tayrakit/interfaces.py
tayrakit.egg-info/PKG-INFO
tayrakit.egg-info/SOURCES.txt
tayrakit.egg-info/dependency_links.txt
tayrakit.egg-info/entry_points.txt
tayrakit.egg-info/namespace_packages.txt
tayrakit.egg-info/not-zip-safe
tayrakit.egg-info/requires.txt
tayrakit.egg-info/top_level.txt
tayrakit/plugins/pluggdapps_footer.ttl
tayrakit/plugins/tbreadcrumbs.ttl